areciboware
