Metadata-Version: 1.0
Name: areciboware
Version: 1.0b1
Summary: Arecibo error logging WSGI middleware
Home-page: http://pypi.python.org/pypi/areciboware
Author: Wichert Akkerman
Author-email: wichert@wiggy.net
License: BSD
Keywords: arecibo WSGI middleware
Platform: UNKNOWN
Classifier: Development Status :: 4 - Beta
Classifier: Intended Audience :: Developers
Classifier: Intended Audience :: System Administrators
Classifier: License :: OSI Approved :: BSD License
Classifier: Operating System :: OS Independent
Classifier: Programming Language :: Python :: 2
Classifier: Topic :: Software Development :: Libraries :: Python Modules
Classifier: Topic :: Internet :: WWW/HTTP :: WSGI :: Middleware
